grpc_reflection-stubs/METADATA.toml
grpc_reflection-stubs/__init__.pyi
grpc_reflection-stubs/py.typed
grpc_reflection-stubs/v1alpha/__init__.pyi
grpc_reflection-stubs/v1alpha/_async.pyi
grpc_reflection-stubs/v1alpha/_base.pyi
grpc_reflection-stubs/v1alpha/proto_reflection_descriptor_database.pyi
grpc_reflection-stubs/v1alpha/reflection.pyi
grpc_reflection-stubs/v1alpha/reflection_pb2.pyi
grpc_reflection-stubs/v1alpha/reflection_pb2_grpc.pyi
types_grpcio_reflection-1.0.0.20250506.dist-info/licenses/LICENSE
types_grpcio_reflection-1.0.0.20250506.dist-info/METADATA
types_grpcio_reflection-1.0.0.20250506.dist-info/WHEEL
types_grpcio_reflection-1.0.0.20250506.dist-info/top_level.txt
types_grpcio_reflection-1.0.0.20250506.dist-info/RECORD
